{
    "location": "http://play.last.fm/user/324b6fb470d916592337ef831dc10d80.mp3",
    "title": "All I Need is a Miracle",
    "identifier": "1019751",
    "album": "Favourites: The Very Best Of",
    "creator": "Mike & The Mechanics",
    "duration": "252000",
    "image": "http://userserve-ak.last.fm/serve/174s/20379973.jpg",
    "extension": {
        "trackauth": "85834",
        "albumid": "2150709",
        "artistid": "1000520",
        "recording": "1019751",
        "artistpage": "http://www.last.fm/music/Mike+&+The+Mechanics",
        "albumpage": "http://www.last.fm/music/Mike+&+The+Mechanics/Favourites:+The+Very+Best+Of",
        "trackpage": "http://www.last.fm/music/Mike+&+The+Mechanics/_/All+I+Need+is+a+Miracle",
        "buyTrackURL": "",
        "buyAlbumURL": "",
        "freeTrackURL": "",
        "loved": "0",
        "streamid": "b06414565f79f265",
        "@attr": {
            "application": "http://www.last.fm"
        }
    },
    "context": [
        {
            "username": "marekventur",
            "userplaycount": "6",
            "userloved": "0"
        },
        {
            "username": "eartle",
            "userplaycount": "1",
            "userloved": "1"
        }
    ],
    "timestamp": 1376477693979
}
